drf_dynamic_fields/__init__.py
drf_dynamic_fields/mixins.py
drf_dynamic_fields_mixin-0.1.0.dist-info/DESCRIPTION.rst
drf_dynamic_fields_mixin-0.1.0.dist-info/LICENSE.txt
drf_dynamic_fields_mixin-0.1.0.dist-info/METADATA
drf_dynamic_fields_mixin-0.1.0.dist-info/metadata.json
drf_dynamic_fields_mixin-0.1.0.dist-info/RECORD
drf_dynamic_fields_mixin-0.1.0.dist-info/top_level.txt
drf_dynamic_fields_mixin-0.1.0.dist-info/WHEEL
