Metadata-Version: 2.0
Name: drf-dynamic-fields-mixin
Version: 0.1.0
Summary: A mixin to make Django Rest Framework serializers dynamically configurable.
Home-page: https://github.com/bellhops/drf_dynamic_fields_mixin
Author: Forrest Pruitt
Author-email: forrest.pruitt@getbellhops.com
License: MIT
Keywords: django-rest-framework-dynamic-fields
Platform: UNKNOWN
Classifier: Development Status :: 3 - Alpha
Classifier: Framework :: Django
Classifier: Intended Audience :: Developers
Classifier: License :: OSI Approved :: MIT License
Classifier: Natural Language :: English
Classifier: Framework :: Django
Classifier: Framework :: Django :: 1.6
Classifier: Framework :: Django :: 1.7
Classifier: Framework :: Django :: 1.8
Classifier: Programming Language :: Python :: 2
Classifier: Programming Language :: Python :: 2.6
Classifier: Programming Language :: Python :: 2.7
Classifier: Programming Language :: Python :: 3
Classifier: Programming Language :: Python :: 3.3
Classifier: Programming Language :: Python :: 3.4
Classifier: Programming Language :: Python :: 3.5
Requires-Dist: djangorestframework
